[
  {
    "question": "What is the deadline for annual reporting?",
    "answer": "March 31st of each year."
  },
  {
    "question": "How often should risk assessments be performed?",
    "answer": "At least annually or when significant changes occur."
  },
  {
    "question": "Who is responsible for maintaining the compliance checklist?",
    "answer": "The Chief Compliance Officer."
  },
  {
    "question": "What is the retention period for customer data?",
    "answer": "7 years from the end of the business relationship."
  },
  {
    "question": "How frequently should employee compliance training be conducted?",
    "answer": "Annually, with additional training for new hires and when regulations change significantly."
  }
]
